{
  "timestamp": "2025-09-18T13:51:59.197789",
  "article_count": 60,
  "avg_sentiment": 0.13500000000000006,
  "news_intensity": 1.0,
  "volatility_score": 12,
  "events": {
    "fomc_detected": false,
    "cpi_detected": false,
    "nfp_detected": false,
    "earnings_detected": true,
    "panic_detected": false,
    "euphoria_detected": false,
    "major_event_score": 12
  },
  "regime_hint": "neutral",
  "articles": [
    {
      "title": "Putting fizz into PepsiCo: weighing up activist advice for US giant",
      "summary": "",
      "published": "2025-09-18T13:44:57Z",
      "link": "https://finance.yahoo.com/news/putting-fizz-pepsico-weighing-activist-121111810.html",
      "source": "yahoo_finance",
      "sentiment": 0.2,
      "has_numbers": false
    },
    {
      "title": "AmEx upgrades Platinum cards with $3,500 annual perks, hikes fee by $200",
      "summary": "",
      "published": "2025-09-18T11:24:41Z",
      "link": "https://finance.yahoo.com/news/amex-upgrades-platinum-cards-3-112441383.html",
      "source": "yahoo_finance",
      "sentiment": 0.2,
      "has_numbers": false
    },
    {
      "title": "Hain Celestial Group (HAIN) Detracted in Q2. Here\u2019s Why",
      "summary": "",
      "published": "2025-09-18T13:35:36Z",
      "link": "https://finance.yahoo.com/news/hain-celestial-group-hain-detracted-133536649.html",
      "source": "yahoo_finance",
      "sentiment": 0.2,
      "has_numbers": false
    },
    {
      "title": "Roche Digs Into Obesity-Tied Diseases With $3.5 Billion 89bio Buyout",
      "summary": "",
      "published": "2025-09-18T13:34:26Z",
      "link": "https://www.investors.com/news/technology/roche-89bio-acquisition-mash-obesity/?src=A00220&yptr=yahoo",
      "source": "yahoo_finance",
      "sentiment": 0.2,
      "has_numbers": false
    },
    {
      "title": "Stock market today: Nasdaq, Dow, S&P 500 rise after Fed signals more cuts, Nvidia bets on Intel",
      "summary": "",
      "published": "2025-09-17T23:14:48Z",
      "link": "https://finance.yahoo.com/news/live/stock-market-today-nasdaq-dow-sp-500-rise-after-fed-signals-more-cuts-nvidia-bets-on-intel-231448487.html",
      "source": "yahoo_finance",
      "sentiment": 0.0,
      "has_numbers": false
    },
    {
      "title": "Daily Spotlight: Fed Back on the Reduction Track",
      "summary": "",
      "published": "2025-09-18T11:30:52Z",
      "link": "https://finance.yahoo.com/research/reports/ARGUS_44741_MarketOutlook_1758195052000?yptr=yahoo&ncid=yahooproperties_plusresear_nm5q6ze1cei",
      "source": "yahoo_finance",
      "sentiment": 0.0,
      "has_numbers": false
    },
    {
      "title": "Target initiated, Nike upgraded: Wall Street's top analyst calls",
      "summary": "",
      "published": "2025-09-18T13:38:40Z",
      "link": "https://finance.yahoo.com/news/target-initiated-nike-upgraded-wall-133840821.html",
      "source": "yahoo_finance",
      "sentiment": 0.4,
      "has_numbers": false
    },
    {
      "title": "Madison Small Cap Fund Sold Hillman Solutions Corp. (HLMN) for Better Opportunities",
      "summary": "",
      "published": "2025-09-18T13:32:39Z",
      "link": "https://finance.yahoo.com/news/madison-small-cap-fund-sold-133239760.html",
      "source": "yahoo_finance",
      "sentiment": 0.0,
      "has_numbers": false
    },
    {
      "title": "Intel stock surges as Nvidia announces $5 billion stake in company",
      "summary": "",
      "published": "2025-09-18T13:32:04Z",
      "link": "https://finance.yahoo.com/news/intel-stock-surges-as-nvidia-announces-5-billion-stake-in-company-133204180.html",
      "source": "yahoo_finance",
      "sentiment": 0.3,
      "has_numbers": false
    },
    {
      "title": "Why This Hydrogen Stock Is Up 80% Since Missing Earnings And Keeps Moving Higher",
      "summary": "",
      "published": "2025-09-18T13:29:06Z",
      "link": "https://www.investors.com/news/fuelcell-stock-has-soared-since-earnings-and-keeps-moving-higher/?src=A00220&yptr=yahoo",
      "source": "yahoo_finance",
      "sentiment": 0.2,
      "has_numbers": true
    },
    {
      "title": "Did you dawdle on that new heat pump or EV? Better move fast to get those tax credits",
      "summary": "",
      "published": "2025-09-18T13:28:08Z",
      "link": "https://finance.yahoo.com/news/did-dawdle-heat-pump-ev-132808297.html",
      "source": "yahoo_finance",
      "sentiment": 0.0,
      "has_numbers": false
    },
    {
      "title": "Technical Assessment: Bullish in the Intermediate-Term",
      "summary": "",
      "published": "2025-09-18T11:30:24Z",
      "link": "https://finance.yahoo.com/research/reports/ARGUS_44740_TechnicalAnalysis_1758195024000?yptr=yahoo&ncid=yahooproperties_plusresear_nm5q6ze1cei",
      "source": "yahoo_finance",
      "sentiment": 0.2,
      "has_numbers": false
    },
    {
      "title": "Could your employer take away your 401(k) match? Sherwin-Williams just did it.",
      "summary": "",
      "published": "2025-09-17T16:42:00Z",
      "link": "https://finance.yahoo.com/news/could-employer-away-401-k-193800832.html",
      "source": "yahoo_finance",
      "sentiment": 0.0,
      "has_numbers": false
    },
    {
      "title": "CrowdStrike Jumps After Guiding Key Growth Metric Above Views",
      "summary": "",
      "published": "2025-09-18T13:26:30Z",
      "link": "https://www.investors.com/news/technology/crowdstrike-stock-crwd-cybersecurity-fiscal-2027-arr-guidance/?src=A00220&yptr=yahoo",
      "source": "yahoo_finance",
      "sentiment": 0.2,
      "has_numbers": false
    },
    {
      "title": "Is The Hanover Insurance Group (THG) a High-Quality P&C Company?",
      "summary": "",
      "published": "2025-09-18T13:24:00Z",
      "link": "https://finance.yahoo.com/news/hanover-insurance-group-thg-high-132400978.html",
      "source": "yahoo_finance",
      "sentiment": 0.2,
      "has_numbers": false
    },
    {
      "title": "Madison Small Cap Fund Trimmed LegalZoom.com (LZ) in Q2",
      "summary": "",
      "published": "2025-09-18T13:21:18Z",
      "link": "https://finance.yahoo.com/news/madison-small-cap-fund-trimmed-132118256.html",
      "source": "yahoo_finance",
      "sentiment": 0.0,
      "has_numbers": false
    },
    {
      "title": "Stock Market Today: Dow Rallies After Rate Cut, Surprise Jobless Claims; Nvidia Climbs On Intel Stake (Live Coverage)",
      "summary": "",
      "published": "2025-09-18T13:21:01Z",
      "link": "https://www.investors.com/market-trend/stock-market-today/dow-jones-sp500-nasdaq-jobless-claims-nvidia-stock-nvda-intel-intc/?src=A00220&yptr=yahoo",
      "source": "yahoo_finance",
      "sentiment": 0.0,
      "has_numbers": false
    },
    {
      "title": "Analyst Report: Kroger Co.",
      "summary": "",
      "published": "2025-09-18T11:00:05Z",
      "link": "https://finance.yahoo.com/research/reports/ARGUS_3129_AnalystReport_1758193205000?yptr=yahoo&ncid=yahooproperties_plusresear_nm5q6ze1cei",
      "source": "yahoo_finance",
      "sentiment": 0.0,
      "has_numbers": false
    },
    {
      "title": "Trump Jr.-Linked Thumzup Stock Sinks 7.7% After $2M Dogecoin Bet",
      "summary": "",
      "published": "2025-09-18T13:32:08Z",
      "link": "https://finance.yahoo.com/news/trump-jr-linked-thumzup-stock-133208974.html",
      "source": "yahoo_finance",
      "sentiment": 0.2,
      "has_numbers": true
    },
    {
      "title": "Should You Be Excited About Shake Shack\u2019s (SHAK) Long-Term Prospects?",
      "summary": "",
      "published": "2025-09-18T13:18:37Z",
      "link": "https://finance.yahoo.com/news/excited-shake-shack-shak-long-131837916.html",
      "source": "yahoo_finance",
      "sentiment": 0.2,
      "has_numbers": false
    },
    {
      "title": "Putting fizz into PepsiCo: weighing up activist advice for US giant",
      "summary": "",
      "published": "2025-09-18T13:44:57Z",
      "link": "https://finance.yahoo.com/news/putting-fizz-pepsico-weighing-activist-121111810.html",
      "source": "yahoo_finance",
      "sentiment": 0.2,
      "has_numbers": false
    },
    {
      "title": "AmEx upgrades Platinum cards with $3,500 annual perks, hikes fee by $200",
      "summary": "",
      "published": "2025-09-18T11:24:41Z",
      "link": "https://finance.yahoo.com/news/amex-upgrades-platinum-cards-3-112441383.html",
      "source": "yahoo_finance",
      "sentiment": 0.2,
      "has_numbers": false
    },
    {
      "title": "Hain Celestial Group (HAIN) Detracted in Q2. Here\u2019s Why",
      "summary": "",
      "published": "2025-09-18T13:35:36Z",
      "link": "https://finance.yahoo.com/news/hain-celestial-group-hain-detracted-133536649.html",
      "source": "yahoo_finance",
      "sentiment": 0.2,
      "has_numbers": false
    },
    {
      "title": "Roche Digs Into Obesity-Tied Diseases With $3.5 Billion 89bio Buyout",
      "summary": "",
      "published": "2025-09-18T13:34:26Z",
      "link": "https://www.investors.com/news/technology/roche-89bio-acquisition-mash-obesity/?src=A00220&yptr=yahoo",
      "source": "yahoo_finance",
      "sentiment": 0.2,
      "has_numbers": false
    },
    {
      "title": "Stock market today: Nasdaq, Dow, S&P 500 rise after Fed signals more cuts, Nvidia bets on Intel",
      "summary": "",
      "published": "2025-09-17T23:14:48Z",
      "link": "https://finance.yahoo.com/news/live/stock-market-today-nasdaq-dow-sp-500-rise-after-fed-signals-more-cuts-nvidia-bets-on-intel-231448487.html",
      "source": "yahoo_finance",
      "sentiment": 0.0,
      "has_numbers": false
    },
    {
      "title": "Daily Spotlight: Fed Back on the Reduction Track",
      "summary": "",
      "published": "2025-09-18T11:30:52Z",
      "link": "https://finance.yahoo.com/research/reports/ARGUS_44741_MarketOutlook_1758195052000?yptr=yahoo&ncid=yahooproperties_plusresear_nm5q6ze1cei",
      "source": "yahoo_finance",
      "sentiment": 0.0,
      "has_numbers": false
    },
    {
      "title": "Target initiated, Nike upgraded: Wall Street's top analyst calls",
      "summary": "",
      "published": "2025-09-18T13:38:40Z",
      "link": "https://finance.yahoo.com/news/target-initiated-nike-upgraded-wall-133840821.html",
      "source": "yahoo_finance",
      "sentiment": 0.4,
      "has_numbers": false
    },
    {
      "title": "Madison Small Cap Fund Sold Hillman Solutions Corp. (HLMN) for Better Opportunities",
      "summary": "",
      "published": "2025-09-18T13:32:39Z",
      "link": "https://finance.yahoo.com/news/madison-small-cap-fund-sold-133239760.html",
      "source": "yahoo_finance",
      "sentiment": 0.0,
      "has_numbers": false
    },
    {
      "title": "Intel stock surges as Nvidia announces $5 billion stake in company",
      "summary": "",
      "published": "2025-09-18T13:32:04Z",
      "link": "https://finance.yahoo.com/news/intel-stock-surges-as-nvidia-announces-5-billion-stake-in-company-133204180.html",
      "source": "yahoo_finance",
      "sentiment": 0.3,
      "has_numbers": false
    },
    {
      "title": "Why This Hydrogen Stock Is Up 80% Since Missing Earnings And Keeps Moving Higher",
      "summary": "",
      "published": "2025-09-18T13:29:06Z",
      "link": "https://www.investors.com/news/fuelcell-stock-has-soared-since-earnings-and-keeps-moving-higher/?src=A00220&yptr=yahoo",
      "source": "yahoo_finance",
      "sentiment": 0.2,
      "has_numbers": true
    },
    {
      "title": "Did you dawdle on that new heat pump or EV? Better move fast to get those tax credits",
      "summary": "",
      "published": "2025-09-18T13:28:08Z",
      "link": "https://finance.yahoo.com/news/did-dawdle-heat-pump-ev-132808297.html",
      "source": "yahoo_finance",
      "sentiment": 0.0,
      "has_numbers": false
    },
    {
      "title": "Technical Assessment: Bullish in the Intermediate-Term",
      "summary": "",
      "published": "2025-09-18T11:30:24Z",
      "link": "https://finance.yahoo.com/research/reports/ARGUS_44740_TechnicalAnalysis_1758195024000?yptr=yahoo&ncid=yahooproperties_plusresear_nm5q6ze1cei",
      "source": "yahoo_finance",
      "sentiment": 0.2,
      "has_numbers": false
    },
    {
      "title": "Could your employer take away your 401(k) match? Sherwin-Williams just did it.",
      "summary": "",
      "published": "2025-09-17T16:42:00Z",
      "link": "https://finance.yahoo.com/news/could-employer-away-401-k-193800832.html",
      "source": "yahoo_finance",
      "sentiment": 0.0,
      "has_numbers": false
    },
    {
      "title": "CrowdStrike Jumps After Guiding Key Growth Metric Above Views",
      "summary": "",
      "published": "2025-09-18T13:26:30Z",
      "link": "https://www.investors.com/news/technology/crowdstrike-stock-crwd-cybersecurity-fiscal-2027-arr-guidance/?src=A00220&yptr=yahoo",
      "source": "yahoo_finance",
      "sentiment": 0.2,
      "has_numbers": false
    },
    {
      "title": "Is The Hanover Insurance Group (THG) a High-Quality P&C Company?",
      "summary": "",
      "published": "2025-09-18T13:24:00Z",
      "link": "https://finance.yahoo.com/news/hanover-insurance-group-thg-high-132400978.html",
      "source": "yahoo_finance",
      "sentiment": 0.2,
      "has_numbers": false
    },
    {
      "title": "Madison Small Cap Fund Trimmed LegalZoom.com (LZ) in Q2",
      "summary": "",
      "published": "2025-09-18T13:21:18Z",
      "link": "https://finance.yahoo.com/news/madison-small-cap-fund-trimmed-132118256.html",
      "source": "yahoo_finance",
      "sentiment": 0.0,
      "has_numbers": false
    },
    {
      "title": "Stock Market Today: Dow Rallies After Rate Cut, Surprise Jobless Claims; Nvidia Climbs On Intel Stake (Live Coverage)",
      "summary": "",
      "published": "2025-09-18T13:21:01Z",
      "link": "https://www.investors.com/market-trend/stock-market-today/dow-jones-sp500-nasdaq-jobless-claims-nvidia-stock-nvda-intel-intc/?src=A00220&yptr=yahoo",
      "source": "yahoo_finance",
      "sentiment": 0.0,
      "has_numbers": false
    },
    {
      "title": "Analyst Report: Kroger Co.",
      "summary": "",
      "published": "2025-09-18T11:00:05Z",
      "link": "https://finance.yahoo.com/research/reports/ARGUS_3129_AnalystReport_1758193205000?yptr=yahoo&ncid=yahooproperties_plusresear_nm5q6ze1cei",
      "source": "yahoo_finance",
      "sentiment": 0.0,
      "has_numbers": false
    },
    {
      "title": "Trump Jr.-Linked Thumzup Stock Sinks 7.7% After $2M Dogecoin Bet",
      "summary": "",
      "published": "2025-09-18T13:32:08Z",
      "link": "https://finance.yahoo.com/news/trump-jr-linked-thumzup-stock-133208974.html",
      "source": "yahoo_finance",
      "sentiment": 0.2,
      "has_numbers": true
    },
    {
      "title": "Should You Be Excited About Shake Shack\u2019s (SHAK) Long-Term Prospects?",
      "summary": "",
      "published": "2025-09-18T13:18:37Z",
      "link": "https://finance.yahoo.com/news/excited-shake-shack-shak-long-131837916.html",
      "source": "yahoo_finance",
      "sentiment": 0.2,
      "has_numbers": false
    },
    {
      "title": "Putting fizz into PepsiCo: weighing up activist advice for US giant",
      "summary": "",
      "published": "2025-09-18T13:44:57Z",
      "link": "https://finance.yahoo.com/news/putting-fizz-pepsico-weighing-activist-121111810.html",
      "source": "yahoo_finance",
      "sentiment": 0.2,
      "has_numbers": false
    },
    {
      "title": "AmEx upgrades Platinum cards with $3,500 annual perks, hikes fee by $200",
      "summary": "",
      "published": "2025-09-18T11:24:41Z",
      "link": "https://finance.yahoo.com/news/amex-upgrades-platinum-cards-3-112441383.html",
      "source": "yahoo_finance",
      "sentiment": 0.2,
      "has_numbers": false
    },
    {
      "title": "Hain Celestial Group (HAIN) Detracted in Q2. Here\u2019s Why",
      "summary": "",
      "published": "2025-09-18T13:35:36Z",
      "link": "https://finance.yahoo.com/news/hain-celestial-group-hain-detracted-133536649.html",
      "source": "yahoo_finance",
      "sentiment": 0.2,
      "has_numbers": false
    },
    {
      "title": "Roche Digs Into Obesity-Tied Diseases With $3.5 Billion 89bio Buyout",
      "summary": "",
      "published": "2025-09-18T13:34:26Z",
      "link": "https://www.investors.com/news/technology/roche-89bio-acquisition-mash-obesity/?src=A00220&yptr=yahoo",
      "source": "yahoo_finance",
      "sentiment": 0.2,
      "has_numbers": false
    },
    {
      "title": "Stock market today: Nasdaq, Dow, S&P 500 rise after Fed signals more cuts, Nvidia bets on Intel",
      "summary": "",
      "published": "2025-09-17T23:14:48Z",
      "link": "https://finance.yahoo.com/news/live/stock-market-today-nasdaq-dow-sp-500-rise-after-fed-signals-more-cuts-nvidia-bets-on-intel-231448487.html",
      "source": "yahoo_finance",
      "sentiment": 0.0,
      "has_numbers": false
    },
    {
      "title": "Daily Spotlight: Fed Back on the Reduction Track",
      "summary": "",
      "published": "2025-09-18T11:30:52Z",
      "link": "https://finance.yahoo.com/research/reports/ARGUS_44741_MarketOutlook_1758195052000?yptr=yahoo&ncid=yahooproperties_plusresear_nm5q6ze1cei",
      "source": "yahoo_finance",
      "sentiment": 0.0,
      "has_numbers": false
    },
    {
      "title": "Target initiated, Nike upgraded: Wall Street's top analyst calls",
      "summary": "",
      "published": "2025-09-18T13:38:40Z",
      "link": "https://finance.yahoo.com/news/target-initiated-nike-upgraded-wall-133840821.html",
      "source": "yahoo_finance",
      "sentiment": 0.4,
      "has_numbers": false
    },
    {
      "title": "Madison Small Cap Fund Sold Hillman Solutions Corp. (HLMN) for Better Opportunities",
      "summary": "",
      "published": "2025-09-18T13:32:39Z",
      "link": "https://finance.yahoo.com/news/madison-small-cap-fund-sold-133239760.html",
      "source": "yahoo_finance",
      "sentiment": 0.0,
      "has_numbers": false
    },
    {
      "title": "Intel stock surges as Nvidia announces $5 billion stake in company",
      "summary": "",
      "published": "2025-09-18T13:32:04Z",
      "link": "https://finance.yahoo.com/news/intel-stock-surges-as-nvidia-announces-5-billion-stake-in-company-133204180.html",
      "source": "yahoo_finance",
      "sentiment": 0.3,
      "has_numbers": false
    },
    {
      "title": "Why This Hydrogen Stock Is Up 80% Since Missing Earnings And Keeps Moving Higher",
      "summary": "",
      "published": "2025-09-18T13:29:06Z",
      "link": "https://www.investors.com/news/fuelcell-stock-has-soared-since-earnings-and-keeps-moving-higher/?src=A00220&yptr=yahoo",
      "source": "yahoo_finance",
      "sentiment": 0.2,
      "has_numbers": true
    }
  ]
}