{
  "timestamp": "2025-09-16T23:16:37.373330",
  "article_count": 60,
  "avg_sentiment": 0.04833333333333334,
  "news_intensity": 1.0,
  "volatility_score": 0,
  "events": {
    "fomc_detected": false,
    "cpi_detected": false,
    "nfp_detected": false,
    "earnings_detected": false,
    "panic_detected": false,
    "euphoria_detected": false,
    "major_event_score": 0
  },
  "regime_hint": "neutral",
  "articles": [
    {
      "title": "Dogecoin Price Crashes 9%, but Experts Call to Buy DOGE Dips",
      "summary": "",
      "published": "2025-09-15T15:04:05Z",
      "link": "https://finance.yahoo.com/news/dogecoin-price-crashes-9-experts-150405042.html",
      "source": "yahoo_finance",
      "sentiment": -0.1,
      "has_numbers": true
    },
    {
      "title": "Nasdaq Is on Track for Best Start to September Since 2010",
      "summary": "",
      "published": "2025-09-15T15:04:29Z",
      "link": "https://www.barrons.com/livecoverage/stock-market-news-today-091525/card/nasdaq-is-on-track-for-best-start-to-september-since-2010-SAfb72u4r2ameuJZptt1?siteid=yhoof2&yptr=yahoo",
      "source": "yahoo_finance",
      "sentiment": 0.0,
      "has_numbers": false
    },
    {
      "title": "The 3 execs now in a 'horse race' to succeed Moynihan as BofA CEO",
      "summary": "",
      "published": "2025-09-15T15:04:53Z",
      "link": "https://finance.yahoo.com/news/the-3-execs-now-in-a-horse-race-to-succeed-moynihan-as-bofa-ceo-150453437.html",
      "source": "yahoo_finance",
      "sentiment": 0.0,
      "has_numbers": false
    },
    {
      "title": "Oracle Stock Jumps on TikTok Deal Speculation",
      "summary": "",
      "published": "2025-09-15T15:05:00Z",
      "link": "https://www.barrons.com/articles/oracle-stock-price-tiktok-speculation-8ef1fb13?siteid=yhoof2&yptr=yahoo",
      "source": "yahoo_finance",
      "sentiment": 0.0,
      "has_numbers": false
    },
    {
      "title": "Palantir\u2019s Execution Has Been \u2018Stunning.\u2019 Why It Isn\u2019t Time to Buy the Stock.",
      "summary": "",
      "published": "2025-09-15T14:59:00Z",
      "link": "https://www.barrons.com/articles/palantir-stock-price-ai-buy-sell-478e77e9?siteid=yhoof2&yptr=yahoo",
      "source": "yahoo_finance",
      "sentiment": 0.2,
      "has_numbers": false
    },
    {
      "title": "France, Austria and Italy Urge Stronger EU Oversight of Crypto Markets Under MiCA",
      "summary": "",
      "published": "2025-09-15T15:03:04Z",
      "link": "https://finance.yahoo.com/news/france-austria-italy-urge-stronger-150304354.html",
      "source": "yahoo_finance",
      "sentiment": 0.0,
      "has_numbers": false
    },
    {
      "title": "Dollar Could Rise Briefly if Fed Fails to Further Boost Rate-Cut Bets",
      "summary": "",
      "published": "2025-09-15T14:58:00Z",
      "link": "https://www.wsj.com/finance/currencies/asian-currencies-consolidate-amid-cautious-mood-553fbfa3?siteid=yhoof2&yptr=yahoo",
      "source": "yahoo_finance",
      "sentiment": 0.0,
      "has_numbers": false
    },
    {
      "title": "Jim Cramer Believes Oracle Corporation (ORCL)\u2019s Conference Call Was Just \u201cMasterful\u201d",
      "summary": "",
      "published": "2025-09-15T14:56:52Z",
      "link": "https://finance.yahoo.com/news/jim-cramer-believes-oracle-corporation-145652424.html",
      "source": "yahoo_finance",
      "sentiment": 0.0,
      "has_numbers": false
    },
    {
      "title": "Jim Cramer Thought Broadcom Inc. (AVGO) \u201cWould Be Up More\u201d After Oracle\u2019s Conference Call",
      "summary": "",
      "published": "2025-09-15T14:56:32Z",
      "link": "https://finance.yahoo.com/news/jim-cramer-thought-broadcom-inc-145632988.html",
      "source": "yahoo_finance",
      "sentiment": 0.2,
      "has_numbers": false
    },
    {
      "title": "S&P 500 and Nasdaq 100 Post Record Highs on Fed Easing Expectations",
      "summary": "",
      "published": "2025-09-15T15:09:50Z",
      "link": "https://finance.yahoo.com/news/p-500-nasdaq-100-post-150950061.html",
      "source": "yahoo_finance",
      "sentiment": 0.0,
      "has_numbers": false
    },
    {
      "title": "5 Things You Should Never Do If You Want Your Savings To Reach $50K",
      "summary": "",
      "published": "2025-09-15T15:00:26Z",
      "link": "https://finance.yahoo.com/news/5-things-never-want-savings-150026917.html",
      "source": "yahoo_finance",
      "sentiment": 0.0,
      "has_numbers": false
    },
    {
      "title": "Jim Cramer Says Taiwan Semiconductor Manufacturing Company (TSM) Is A \u201cNational Treasure\u201d",
      "summary": "",
      "published": "2025-09-15T14:56:11Z",
      "link": "https://finance.yahoo.com/news/jim-cramer-says-taiwan-semiconductor-145611427.html",
      "source": "yahoo_finance",
      "sentiment": 0.0,
      "has_numbers": false
    },
    {
      "title": "Jim Cramer Praises Klarna Group plc (KLAR)\u2019s Predictive System",
      "summary": "",
      "published": "2025-09-15T14:55:52Z",
      "link": "https://finance.yahoo.com/news/jim-cramer-praises-klarna-group-145552653.html",
      "source": "yahoo_finance",
      "sentiment": 0.2,
      "has_numbers": false
    },
    {
      "title": "Exxon\u2019s New Ally in Fight With Activists: Its Own Retail Investors",
      "summary": "",
      "published": "2025-09-15T14:56:00Z",
      "link": "https://www.wsj.com/business/energy-oil/exxons-new-ally-in-fight-with-activists-its-own-retail-investors-759c0a8a?siteid=yhoof2&yptr=yahoo",
      "source": "yahoo_finance",
      "sentiment": 0.0,
      "has_numbers": false
    },
    {
      "title": "\u201cIt\u2019s Time To Buy\u201d NIKE, Inc. (NKE), Says Jim Cramer",
      "summary": "",
      "published": "2025-09-15T14:55:22Z",
      "link": "https://finance.yahoo.com/news/time-buy-nike-inc-nke-145522188.html",
      "source": "yahoo_finance",
      "sentiment": 0.2,
      "has_numbers": false
    },
    {
      "title": "Analyst Report: Sempra Energy",
      "summary": "",
      "published": "2025-09-16T16:38:36Z",
      "link": "https://finance.yahoo.com/research/reports/ARGUS_3409_AnalystReport_1758040716000?yptr=yahoo&ncid=yahooproperties_plusresear_nm5q6ze1cei",
      "source": "yahoo_finance",
      "sentiment": 0.0,
      "has_numbers": false
    },
    {
      "title": "Tom Lee's Ethereum Treasury BitMine Boosts ETH Holdings to Nearly $10 Billion",
      "summary": "",
      "published": "2025-09-15T14:59:23Z",
      "link": "https://finance.yahoo.com/news/tom-lees-ethereum-treasury-bitmine-145923275.html",
      "source": "yahoo_finance",
      "sentiment": 0.0,
      "has_numbers": false
    },
    {
      "title": "When will mortgage rates go down? They're edging down now, and buyers are noticing.",
      "summary": "",
      "published": "2025-04-22T19:06:10Z",
      "link": "https://finance.yahoo.com/personal-finance/mortgages/article/when-will-mortgage-rates-go-down-theyre-edging-down-now-and-buyers-are-noticing-september-15-2025-190610396.html",
      "source": "yahoo_finance",
      "sentiment": 0.0,
      "has_numbers": false
    },
    {
      "title": "Wells Fargo & Company (WFC)\u2019s CEO Has \u201cDone So Much Good,\u201d Says Jim Cramer",
      "summary": "",
      "published": "2025-09-15T14:55:09Z",
      "link": "https://finance.yahoo.com/news/wells-fargo-company-wfc-ceo-145509256.html",
      "source": "yahoo_finance",
      "sentiment": 0.0,
      "has_numbers": false
    },
    {
      "title": "Jim Cramer Praises JPMorgan Chase & Co. (JPM)\u2019s Work Culture",
      "summary": "",
      "published": "2025-09-15T14:54:32Z",
      "link": "https://finance.yahoo.com/news/jim-cramer-praises-jpmorgan-chase-145432850.html",
      "source": "yahoo_finance",
      "sentiment": 0.0,
      "has_numbers": false
    },
    {
      "title": "Palantir\u2019s Execution Has Been \u2018Stunning.\u2019 Why It Isn\u2019t Time to Buy the Stock.",
      "summary": "",
      "published": "2025-09-15T14:59:00Z",
      "link": "https://www.barrons.com/articles/palantir-stock-price-ai-buy-sell-478e77e9?siteid=yhoof2&yptr=yahoo",
      "source": "yahoo_finance",
      "sentiment": 0.2,
      "has_numbers": false
    },
    {
      "title": "PayPal Adding Crypto to Peer-to-Peer Payments, Allowing Direct Transfer of BTC, ETH, Others",
      "summary": "",
      "published": "2025-09-15T14:58:23Z",
      "link": "https://finance.yahoo.com/news/paypal-adding-crypto-peer-peer-145823890.html",
      "source": "yahoo_finance",
      "sentiment": 0.0,
      "has_numbers": false
    },
    {
      "title": "Jim Cramer Thought Broadcom Inc. (AVGO) \u201cWould Be Up More\u201d After Oracle\u2019s Conference Call",
      "summary": "",
      "published": "2025-09-15T14:56:32Z",
      "link": "https://finance.yahoo.com/news/jim-cramer-thought-broadcom-inc-145632988.html",
      "source": "yahoo_finance",
      "sentiment": 0.2,
      "has_numbers": false
    },
    {
      "title": "Dollar Could Rise Briefly if Fed Fails to Further Boost Rate-Cut Bets",
      "summary": "",
      "published": "2025-09-15T14:58:00Z",
      "link": "https://www.wsj.com/finance/currencies/asian-currencies-consolidate-amid-cautious-mood-553fbfa3?siteid=yhoof2&yptr=yahoo",
      "source": "yahoo_finance",
      "sentiment": 0.0,
      "has_numbers": false
    },
    {
      "title": "Jim Cramer Says Taiwan Semiconductor Manufacturing Company (TSM) Is A \u201cNational Treasure\u201d",
      "summary": "",
      "published": "2025-09-15T14:56:11Z",
      "link": "https://finance.yahoo.com/news/jim-cramer-says-taiwan-semiconductor-145611427.html",
      "source": "yahoo_finance",
      "sentiment": 0.0,
      "has_numbers": false
    },
    {
      "title": "Jim Cramer Praises Klarna Group plc (KLAR)\u2019s Predictive System",
      "summary": "",
      "published": "2025-09-15T14:55:52Z",
      "link": "https://finance.yahoo.com/news/jim-cramer-praises-klarna-group-145552653.html",
      "source": "yahoo_finance",
      "sentiment": 0.2,
      "has_numbers": false
    },
    {
      "title": "Tom Lee's Ethereum Treasury BitMine Boosts ETH Holdings to Nearly $10 Billion",
      "summary": "",
      "published": "2025-09-15T14:59:23Z",
      "link": "https://finance.yahoo.com/news/tom-lees-ethereum-treasury-bitmine-145923275.html",
      "source": "yahoo_finance",
      "sentiment": 0.0,
      "has_numbers": false
    },
    {
      "title": "Jim Cramer Believes Oracle Corporation (ORCL)\u2019s Conference Call Was Just \u201cMasterful\u201d",
      "summary": "",
      "published": "2025-09-15T14:56:52Z",
      "link": "https://finance.yahoo.com/news/jim-cramer-believes-oracle-corporation-145652424.html",
      "source": "yahoo_finance",
      "sentiment": 0.0,
      "has_numbers": false
    },
    {
      "title": "Wells Fargo & Company (WFC)\u2019s CEO Has \u201cDone So Much Good,\u201d Says Jim Cramer",
      "summary": "",
      "published": "2025-09-15T14:55:09Z",
      "link": "https://finance.yahoo.com/news/wells-fargo-company-wfc-ceo-145509256.html",
      "source": "yahoo_finance",
      "sentiment": 0.0,
      "has_numbers": false
    },
    {
      "title": "Exxon\u2019s New Ally in Fight With Activists: Its Own Retail Investors",
      "summary": "",
      "published": "2025-09-15T14:56:00Z",
      "link": "https://www.wsj.com/business/energy-oil/exxons-new-ally-in-fight-with-activists-its-own-retail-investors-759c0a8a?siteid=yhoof2&yptr=yahoo",
      "source": "yahoo_finance",
      "sentiment": 0.0,
      "has_numbers": false
    },
    {
      "title": "Jim Cramer Praises JPMorgan Chase & Co. (JPM)\u2019s Work Culture",
      "summary": "",
      "published": "2025-09-15T14:54:32Z",
      "link": "https://finance.yahoo.com/news/jim-cramer-praises-jpmorgan-chase-145432850.html",
      "source": "yahoo_finance",
      "sentiment": 0.0,
      "has_numbers": false
    },
    {
      "title": "5 Things You Should Never Do If You Want Your Savings To Reach $50K",
      "summary": "",
      "published": "2025-09-15T15:00:26Z",
      "link": "https://finance.yahoo.com/news/5-things-never-want-savings-150026917.html",
      "source": "yahoo_finance",
      "sentiment": 0.0,
      "has_numbers": false
    },
    {
      "title": "\u201cPeople Are Getting Greedy,\u201d Says Jim Cramer When Discussing American Express Company (AXP)",
      "summary": "",
      "published": "2025-09-15T14:54:15Z",
      "link": "https://finance.yahoo.com/news/people-getting-greedy-says-jim-145415228.html",
      "source": "yahoo_finance",
      "sentiment": 0.0,
      "has_numbers": false
    },
    {
      "title": "\u201cIt\u2019s Time To Buy\u201d NIKE, Inc. (NKE), Says Jim Cramer",
      "summary": "",
      "published": "2025-09-15T14:55:22Z",
      "link": "https://finance.yahoo.com/news/time-buy-nike-inc-nke-145522188.html",
      "source": "yahoo_finance",
      "sentiment": 0.2,
      "has_numbers": false
    },
    {
      "title": "Is Tractor Supply Stock Underperforming the S&P 500?",
      "summary": "",
      "published": "2025-09-15T14:53:44Z",
      "link": "https://finance.yahoo.com/news/tractor-supply-stock-underperforming-p-145344893.html",
      "source": "yahoo_finance",
      "sentiment": 0.2,
      "has_numbers": false
    },
    {
      "title": "Analyst Report: Sempra Energy",
      "summary": "",
      "published": "2025-09-16T16:38:36Z",
      "link": "https://finance.yahoo.com/research/reports/ARGUS_3409_AnalystReport_1758040716000?yptr=yahoo&ncid=yahooproperties_plusresear_nm5q6ze1cei",
      "source": "yahoo_finance",
      "sentiment": 0.0,
      "has_numbers": false
    },
    {
      "title": "Nasdaq Is on Track for Best Start to September Since 2010",
      "summary": "",
      "published": "2025-09-15T15:04:29Z",
      "link": "https://www.barrons.com/livecoverage/stock-market-news-today-091525/card/nasdaq-is-on-track-for-best-start-to-september-since-2010-SAfb72u4r2ameuJZptt1?siteid=yhoof2&yptr=yahoo",
      "source": "yahoo_finance",
      "sentiment": 0.0,
      "has_numbers": false
    },
    {
      "title": "Want To Earn What Your CEO Makes? 5 Shocking Truths About Your Paycheck Differences",
      "summary": "",
      "published": "2025-09-15T14:55:24Z",
      "link": "https://finance.yahoo.com/news/want-earn-ceo-makes-5-145524258.html",
      "source": "yahoo_finance",
      "sentiment": 0.0,
      "has_numbers": false
    },
    {
      "title": "Exxon to offer auto-voting to counter shareholder activism",
      "summary": "",
      "published": "2025-09-15T14:52:04Z",
      "link": "https://finance.yahoo.com/news/exxon-offer-auto-voting-counter-145204542.html",
      "source": "yahoo_finance",
      "sentiment": 0.0,
      "has_numbers": false
    },
    {
      "title": "The 3 execs now in a 'horse race' to succeed Moynihan as BofA CEO",
      "summary": "",
      "published": "2025-09-15T15:04:53Z",
      "link": "https://finance.yahoo.com/news/the-3-execs-now-in-a-horse-race-to-succeed-moynihan-as-bofa-ceo-150453437.html",
      "source": "yahoo_finance",
      "sentiment": 0.0,
      "has_numbers": false
    },
    {
      "title": "S&P 500 and Nasdaq 100 Post Record Highs on Fed Easing Expectations",
      "summary": "",
      "published": "2025-09-15T15:09:50Z",
      "link": "https://finance.yahoo.com/news/p-500-nasdaq-100-post-150950061.html",
      "source": "yahoo_finance",
      "sentiment": 0.0,
      "has_numbers": false
    },
    {
      "title": "When will mortgage rates go down? They're edging down now, and buyers are noticing.",
      "summary": "",
      "published": "2025-04-22T19:06:10Z",
      "link": "https://finance.yahoo.com/personal-finance/mortgages/article/when-will-mortgage-rates-go-down-theyre-edging-down-now-and-buyers-are-noticing-september-15-2025-190610396.html",
      "source": "yahoo_finance",
      "sentiment": 0.0,
      "has_numbers": false
    },
    {
      "title": "The 3 execs now in a 'horse race' to succeed Moynihan as BofA CEO",
      "summary": "",
      "published": "2025-09-15T15:04:53Z",
      "link": "https://finance.yahoo.com/news/the-3-execs-now-in-a-horse-race-to-succeed-moynihan-as-bofa-ceo-150453437.html",
      "source": "yahoo_finance",
      "sentiment": 0.0,
      "has_numbers": false
    },
    {
      "title": "Oracle Stock Jumps on TikTok Deal Speculation",
      "summary": "",
      "published": "2025-09-15T15:05:00Z",
      "link": "https://www.barrons.com/articles/oracle-stock-price-tiktok-speculation-8ef1fb13?siteid=yhoof2&yptr=yahoo",
      "source": "yahoo_finance",
      "sentiment": 0.0,
      "has_numbers": false
    },
    {
      "title": "Nasdaq Is on Track for Best Start to September Since 2010",
      "summary": "",
      "published": "2025-09-15T15:04:29Z",
      "link": "https://www.barrons.com/livecoverage/stock-market-news-today-091525/card/nasdaq-is-on-track-for-best-start-to-september-since-2010-SAfb72u4r2ameuJZptt1?siteid=yhoof2&yptr=yahoo",
      "source": "yahoo_finance",
      "sentiment": 0.0,
      "has_numbers": false
    },
    {
      "title": "Dogecoin Price Crashes 9%, but Experts Call to Buy DOGE Dips",
      "summary": "",
      "published": "2025-09-15T15:04:05Z",
      "link": "https://finance.yahoo.com/news/dogecoin-price-crashes-9-experts-150405042.html",
      "source": "yahoo_finance",
      "sentiment": -0.1,
      "has_numbers": true
    },
    {
      "title": "Is Elon\u2019s Insider Buying a Bullish Signal for Overbought Tesla Stock, or More Noise?",
      "summary": "",
      "published": "2025-09-15T15:13:21Z",
      "link": "https://finance.yahoo.com/news/elon-insider-buying-bullish-signal-151321355.html",
      "source": "yahoo_finance",
      "sentiment": 0.4,
      "has_numbers": false
    },
    {
      "title": "Canada Factory and Wholesale Sales Continue to Bounce Back, Recovering From Tariff Hit",
      "summary": "",
      "published": "2025-09-15T15:15:00Z",
      "link": "https://www.wsj.com/articles/canada-factory-and-wholesale-sales-continue-to-bounce-back-recovering-from-tariff-hit-ed3e24ae?siteid=yhoof2&yptr=yahoo",
      "source": "yahoo_finance",
      "sentiment": 0.1,
      "has_numbers": false
    },
    {
      "title": "Will Mag 7 Stocks Rally Post Fed? What the Charts of Microsoft, Tesla, Meta Say.",
      "summary": "",
      "published": "2025-09-15T15:17:00Z",
      "link": "https://www.barrons.com/articles/mag-7-stocks-microsoft-tesla-meta-charts-9fb8dc1d?siteid=yhoof2&yptr=yahoo",
      "source": "yahoo_finance",
      "sentiment": 0.2,
      "has_numbers": false
    },
    {
      "title": "Palantir\u2019s Execution Has Been \u2018Stunning.\u2019 Why It Isn\u2019t Time to Buy the Stock.",
      "summary": "",
      "published": "2025-09-15T14:59:00Z",
      "link": "https://www.barrons.com/articles/palantir-stock-price-ai-buy-sell-478e77e9?siteid=yhoof2&yptr=yahoo",
      "source": "yahoo_finance",
      "sentiment": 0.2,
      "has_numbers": false
    }
  ]
}