{
  "SPY": {
    "timestamp": "2025-09-16T19:31:29.600862",
    "category": "indices",
    "price": 659.9500122070312,
    "volume": 168871,
    "features": [
      660.1400146484375,
      660.1849975585938,
      659.9500122070312,
      659.9500122070312,
      0.168871,
      -0.00028782142756099584,
      0.0,
      0.0,
      0.0,
      0.0,
      0.0,
      0.0,
      0.0,
      0.0,
      0.0,
      0.0,
      0.0,
      0.0,
      0.0,
      0.0
    ],
    "status": "success"
  },
  "QQQ": {
    "timestamp": "2025-09-16T19:31:30.899951",
    "category": "indices",
    "price": 591.4199829101562,
    "volume": 144908,
    "features": [
      591.47998046875,
      591.5150146484375,
      591.4199829101562,
      591.4199829101562,
      0.144908,
      -0.00010143633018010469,
      0.0,
      0.0,
      0.0,
      0.0,
      0.0,
      0.0,
      0.0,
      0.0,
      0.0,
      0.0,
      0.0,
      0.0,
      0.0,
      0.0
    ],
    "status": "success"
  },
  "IWM": {
    "timestamp": "2025-09-16T19:31:32.438638",
    "category": "indices",
    "price": 237.9600067138672,
    "volume": 67471,
    "features": [
      238.02000427246094,
      238.0800018310547,
      237.9600067138672,
      237.9600067138672,
      0.067471,
      -0.00025206939549950993,
      0.0,
      0.0,
      0.0,
      0.0,
      0.0,
      0.0,
      0.0,
      0.0,
      0.0,
      0.0,
      0.0,
      0.0,
      0.0,
      0.0
    ],
    "status": "success"
  },
  "ES=F": {
    "timestamp": "2025-09-16T19:31:32.837870",
    "category": "futures",
    "price": 6675.25,
    "volume": 583719,
    "features": [
      6673.75,
      6675.25,
      6616.25,
      6675.25,
      0.583719,
      0.00022476119123431354,
      0.0,
      0.0,
      0.0,
      0.0,
      0.0,
      0.0,
      0.0,
      0.0,
      0.0,
      0.0,
      0.0,
      0.0,
      0.0,
      0.0
    ],
    "status": "success"
  },
  "NQ=F": {
    "timestamp": "2025-09-16T19:31:34.166108",
    "category": "futures",
    "price": 24315.5,
    "volume": 2086,
    "features": [
      24549.5,
      24553.5,
      24307.0,
      24315.5,
      0.002086,
      -0.009531762357685493,
      0.0,
      0.0,
      0.0,
      0.0,
      0.0,
      0.0,
      0.0,
      0.0,
      0.0,
      0.0,
      0.0,
      0.0,
      0.0,
      0.0
    ],
    "status": "success"
  },
  "^VIX": {
    "timestamp": "2025-09-16T19:31:34.378522",
    "category": "volatility",
    "price": 16.06999969482422,
    "volume": 0,
    "features": [
      16.040000915527344,
      16.06999969482422,
      16.040000915527344,
      16.06999969482422,
      0.0,
      0.0018702479790905135,
      0.0,
      0.0,
      0.0,
      0.0,
      0.0,
      0.0,
      0.0,
      0.0,
      0.0,
      0.0,
      0.0,
      0.0,
      0.0,
      0.0
    ],
    "status": "success"
  }
}