{
  "SPY": {
    "timestamp": "2025-09-22T15:36:53.141111",
    "category": "indices",
    "price": 664.6699829101562,
    "volume": 199403,
    "features": [
      664.6649780273438,
      664.8599853515625,
      664.5999755859375,
      664.6699829101562,
      0.199403,
      7.529933091034779e-06,
      0.0,
      0.0,
      0.0,
      0.0,
      0.0,
      0.0,
      0.0,
      0.0,
      0.0,
      0.0,
      0.0,
      0.0,
      0.0,
      0.0
    ],
    "status": "success"
  },
  "QQQ": {
    "timestamp": "2025-09-22T15:36:54.302226",
    "category": "indices",
    "price": 599.8800048828125,
    "volume": 196500,
    "features": [
      599.8699951171875,
      600.114990234375,
      599.77001953125,
      599.8800048828125,
      0.1965,
      1.668655826508633e-05,
      0.0,
      0.0,
      0.0,
      0.0,
      0.0,
      0.0,
      0.0,
      0.0,
      0.0,
      0.0,
      0.0,
      0.0,
      0.0,
      0.0
    ],
    "status": "success"
  },
  "IWM": {
    "timestamp": "2025-09-22T15:36:55.444800",
    "category": "indices",
    "price": 243.38999938964844,
    "volume": 80929,
    "features": [
      243.3300018310547,
      243.38999938964844,
      243.25,
      243.38999938964844,
      0.080929,
      0.0002465686850872036,
      0.0,
      0.0,
      0.0,
      0.0,
      0.0,
      0.0,
      0.0,
      0.0,
      0.0,
      0.0,
      0.0,
      0.0,
      0.0,
      0.0
    ],
    "status": "success"
  },
  "ES=F": {
    "timestamp": "2025-09-22T15:36:55.552780",
    "category": "futures",
    "price": 6733.0,
    "volume": 4969,
    "features": [
      6733.5,
      6734.25,
      6732.0,
      6733.0,
      0.004969,
      -7.425558773297691e-05,
      0.0,
      0.0,
      0.0,
      0.0,
      0.0,
      0.0,
      0.0,
      0.0,
      0.0,
      0.0,
      0.0,
      0.0,
      0.0,
      0.0
    ],
    "status": "success"
  },
  "NQ=F": {
    "timestamp": "2025-09-22T15:36:56.725661",
    "category": "futures",
    "price": 24919.75,
    "volume": 2265,
    "features": [
      24918.0,
      24923.5,
      24912.25,
      24919.75,
      0.002265,
      7.023035556625733e-05,
      0.0,
      0.0,
      0.0,
      0.0,
      0.0,
      0.0,
      0.0,
      0.0,
      0.0,
      0.0,
      0.0,
      0.0,
      0.0,
      0.0
    ],
    "status": "success"
  },
  "^VIX": {
    "timestamp": "2025-09-22T15:36:56.933852",
    "category": "volatility",
    "price": 15.869999885559082,
    "volume": 0,
    "features": [
      15.880000114440918,
      15.880000114440918,
      15.859999656677246,
      15.869999885559082,
      0.0,
      -0.0006297373305899382,
      0.0,
      0.0,
      0.0,
      0.0,
      0.0,
      0.0,
      0.0,
      0.0,
      0.0,
      0.0,
      0.0,
      0.0,
      0.0,
      0.0
    ],
    "status": "success"
  }
}