{
  "SPY": {
    "timestamp": "2025-09-05T15:42:54.645517",
    "category": "indices",
    "price": 646.7550048828125,
    "volume": 260020,
    "features": [
      646.260009765625,
      646.7550048828125,
      646.2598876953125,
      646.7550048828125,
      0.26002,
      0.0007659380275858578,
      0.0,
      0.0,
      0.0,
      0.0,
      0.0,
      0.0,
      0.0,
      0.0,
      0.0,
      0.0,
      0.0,
      0.0,
      0.0,
      0.0
    ],
    "status": "success"
  },
  "QQQ": {
    "timestamp": "2025-09-05T15:42:55.885196",
    "category": "indices",
    "price": 575.385009765625,
    "volume": 182759,
    "features": [
      574.9199829101562,
      575.385009765625,
      574.8200073242188,
      575.385009765625,
      0.182759,
      0.0008088549177136891,
      0.0,
      0.0,
      0.0,
      0.0,
      0.0,
      0.0,
      0.0,
      0.0,
      0.0,
      0.0,
      0.0,
      0.0,
      0.0,
      0.0
    ],
    "status": "success"
  },
  "IWM": {
    "timestamp": "2025-09-05T15:42:57.037435",
    "category": "indices",
    "price": 237.1300048828125,
    "volume": 123596,
    "features": [
      236.9550018310547,
      237.1300048828125,
      236.91000366210938,
      237.1300048828125,
      0.123596,
      0.000738549726342502,
      0.0,
      0.0,
      0.0,
      0.0,
      0.0,
      0.0,
      0.0,
      0.0,
      0.0,
      0.0,
      0.0,
      0.0,
      0.0,
      0.0
    ],
    "status": "success"
  },
  "ES=F": {
    "timestamp": "2025-09-05T15:42:57.165220",
    "category": "futures",
    "price": 6476.75,
    "volume": 14056,
    "features": [
      6481.0,
      6482.5,
      6474.75,
      6476.75,
      0.014056,
      -0.0006557629995371085,
      0.0,
      0.0,
      0.0,
      0.0,
      0.0,
      0.0,
      0.0,
      0.0,
      0.0,
      0.0,
      0.0,
      0.0,
      0.0,
      0.0
    ],
    "status": "success"
  },
  "NQ=F": {
    "timestamp": "2025-09-05T15:42:58.272385",
    "category": "futures",
    "price": 23615.0,
    "volume": 5593,
    "features": [
      23633.0,
      23640.0,
      23606.5,
      23615.0,
      0.005593,
      -0.000761646849744002,
      0.0,
      0.0,
      0.0,
      0.0,
      0.0,
      0.0,
      0.0,
      0.0,
      0.0,
      0.0,
      0.0,
      0.0,
      0.0,
      0.0
    ],
    "status": "success"
  },
  "^VIX": {
    "timestamp": "2025-09-05T15:42:58.593785",
    "category": "volatility",
    "price": 16.139999389648438,
    "volume": 0,
    "features": [
      16.149999618530273,
      16.209999084472656,
      16.1299991607666,
      16.139999389648438,
      0.0,
      -0.0006192092333155118,
      0.0,
      0.0,
      0.0,
      0.0,
      0.0,
      0.0,
      0.0,
      0.0,
      0.0,
      0.0,
      0.0,
      0.0,
      0.0,
      0.0
    ],
    "status": "success"
  }
}