{
  "SPY": {
    "timestamp": "2025-09-10T21:16:56.600163",
    "category": "indices",
    "price": 652.2249755859375,
    "volume": 4146224,
    "features": [
      652.2000122070312,
      652.7000122070312,
      652.1799926757812,
      652.2249755859375,
      4.146224,
      3.827564924719098e-05,
      0.0,
      0.0,
      0.0,
      0.0,
      0.0,
      0.0,
      0.0,
      0.0,
      0.0,
      0.0,
      0.0,
      0.0,
      0.0,
      0.0
    ],
    "status": "success"
  },
  "QQQ": {
    "timestamp": "2025-09-10T21:16:57.751715",
    "category": "indices",
    "price": 580.7000122070312,
    "volume": 2148307,
    "features": [
      580.5999755859375,
      581.1400146484375,
      580.5700073242188,
      580.7000122070312,
      2.148307,
      0.00017229870013823844,
      0.0,
      0.0,
      0.0,
      0.0,
      0.0,
      0.0,
      0.0,
      0.0,
      0.0,
      0.0,
      0.0,
      0.0,
      0.0,
      0.0
    ],
    "status": "success"
  },
  "IWM": {
    "timestamp": "2025-09-10T21:16:58.948381",
    "category": "indices",
    "price": 236.4149932861328,
    "volume": 1368006,
    "features": [
      236.4499969482422,
      236.5850067138672,
      236.33999633789062,
      236.4149932861328,
      1.368006,
      -0.0001480383276005588,
      0.0,
      0.0,
      0.0,
      0.0,
      0.0,
      0.0,
      0.0,
      0.0,
      0.0,
      0.0,
      0.0,
      0.0,
      0.0,
      0.0
    ],
    "status": "success"
  },
  "ES=F": {
    "timestamp": "2025-09-10T21:16:59.167091",
    "category": "futures",
    "price": 6536.75,
    "volume": 504,
    "features": [
      6536.75,
      6537.5,
      6536.5,
      6536.75,
      0.000504,
      0.0,
      0.0,
      0.0,
      0.0,
      0.0,
      0.0,
      0.0,
      0.0,
      0.0,
      0.0,
      0.0,
      0.0,
      0.0,
      0.0,
      0.0
    ],
    "status": "success"
  },
  "NQ=F": {
    "timestamp": "2025-09-10T21:17:00.272286",
    "category": "futures",
    "price": 23858.0,
    "volume": 185,
    "features": [
      23859.25,
      23863.0,
      23858.0,
      23858.0,
      0.000185,
      -5.239058226893134e-05,
      0.0,
      0.0,
      0.0,
      0.0,
      0.0,
      0.0,
      0.0,
      0.0,
      0.0,
      0.0,
      0.0,
      0.0,
      0.0,
      0.0
    ],
    "status": "success"
  },
  "^VIX": {
    "timestamp": "2025-09-10T21:17:00.372663",
    "category": "volatility",
    "price": 15.369999885559082,
    "volume": 0,
    "features": [
      15.380000114440918,
      15.399999618530273,
      15.369999885559082,
      15.369999885559082,
      0.0,
      -0.0006502099354632845,
      0.0,
      0.0,
      0.0,
      0.0,
      0.0,
      0.0,
      0.0,
      0.0,
      0.0,
      0.0,
      0.0,
      0.0,
      0.0,
      0.0
    ],
    "status": "success"
  }
}